drb_impl_swift/__init__.py
drb_impl_swift/_version.py
drb_impl_swift/cortex.yml
drb_impl_swift/drb_impl_swift.py
drb_impl_swift/swift_node_factory.py
drb_impl_swift/swift_utils.py
drb_impl_swift-1.0.1.data/data/requirements.txt
drb_impl_swift-1.0.1.dist-info/METADATA
drb_impl_swift-1.0.1.dist-info/WHEEL
drb_impl_swift-1.0.1.dist-info/entry_points.txt
drb_impl_swift-1.0.1.dist-info/top_level.txt
drb_impl_swift-1.0.1.dist-info/RECORD
