Metadata-Version: 2.1
Name: drb-impl-swift
Version: 1.0.1
Summary: DRB Swift implementation
Home-page: https://gitlab.com/drb-python/impl/swift
Author: GAEL Systems
Author-email: drb-python@gael.fr
License: UNKNOWN
Project-URL: Documentation, https://drb-python.gitlab.io/impl/swift/
Project-URL: Source, https://gitlab.com/drb-python/impl/swift
Platform: UNKNOWN
Classifier: Programming Language :: Python :: 3.8
Classifier: License :: OSI Approved :: Apache Software License
Classifier: Operating System :: OS Independent
Requires-Python: >=3.8
Requires-Dist: drb (<1.1.0,>=1.0.1)
Requires-Dist: python-swiftclient
Requires-Dist: drb-impl-http (==1.0.1)
